hg_setup/__init__.py
hg_setup/completion.py
hg_setup/hgrcs.py
hg_setup/init_app.tcss
hg_setup/init_cmd.py
hg_setup/data/bash_completion
hg_setup/data/zsh_completion
hg_setup-0.1.5.dist-info/entry_points.txt
hg_setup-0.1.5.dist-info/licenses/LICENSE
hg_setup-0.1.5.dist-info/WHEEL
hg_setup-0.1.5.dist-info/METADATA
hg_setup-0.1.5.dist-info/RECORD
