Metadata-Version: 2.4
Name: hg-setup
Version: 0.1.5
Summary: Helper for setting up and configuring Mercurial
Author-email: Pierre Augier <pierre.augier@univ-grenoble-alpes.fr>
Requires-Python: >=3.11
License-File: LICENSE
Requires-Dist: click
Requires-Dist: textual
Requires-Dist: rich-click
